django_json_field_schema_validator/__init__.py
django_json_field_schema_validator/validators.py
tests/__init__.py
tests/test_validators.py
django_json_field_schema_validator-0.0.2.dist-info/LICENSE
django_json_field_schema_validator-0.0.2.dist-info/METADATA
django_json_field_schema_validator-0.0.2.dist-info/WHEEL
django_json_field_schema_validator-0.0.2.dist-info/top_level.txt
django_json_field_schema_validator-0.0.2.dist-info/RECORD
