Metadata-Version: 2.1
Name: django-json-field-schema-validator
Version: 0.0.2
Summary: Tiny tool for Django JSONField validation
Home-page: https://github.com/wblxyxolbkhv/django-json-field-schema-validator
Author: Alexey Nikitenko (wblxyxolbkhv)
Author-email: alexey.nikitenko1927@gmail.com
License: UNKNOWN
Project-URL: Source, https://github.com/wblxyxolbkhv/django-json-field-schema-validator
Keywords: django json field schema validator tools
Platform: UNKNOWN
Classifier: Intended Audience :: Developers
Classifier: Topic :: Software Development :: Libraries
Classifier: License :: OSI Approved :: MIT License
Classifier: Programming Language :: Python :: 3
Classifier: Operating System :: OS Independent
Requires-Python: >=3.5, <4
Requires-Dist: Django (>=1.0)
Requires-Dist: jsonschema (>=3.0.0)
